fplab/__init__.py
fplab/enhancement/__init__.py
fplab/enhancement/frequency.py
fplab/enhancement/spatial.py
fplab/intrinsic/__init__.py
fplab/intrinsic/frequency/__init__.py
fplab/intrinsic/frequency/projection.py
fplab/intrinsic/frequency/tools.py
fplab/intrinsic/mask/__init__.py
fplab/intrinsic/multiple/__init__.py
fplab/intrinsic/multiple/transform.py
fplab/intrinsic/orientation/__init__.py
fplab/intrinsic/orientation/gradient.py
fplab/intrinsic/orientation/tools.py
fplab/matching/__init__.py
fplab/matching/matching.py
fplab/minutiae/__init__.py
fplab/tools/__init__.py
fplab/tools/array.py
fplab/tools/image.py
fplab/tools/nbis.py
fplab/tools/tensor.py
fplab-0.0.1.dist-info/LICENSE.txt
fplab-0.0.1.dist-info/METADATA
fplab-0.0.1.dist-info/WHEEL
fplab-0.0.1.dist-info/top_level.txt
fplab-0.0.1.dist-info/RECORD
