Metadata-Version: 2.1
Name: fplab
Version: 0.0.1
Summary: Python3 Package for Fingerprint Processing
Author: Yurun Wang
Author-email: wangyurun@mail.sdu.edu.cn
License: MIT
Keywords: python,fingerprint
Classifier: Programming Language :: Python :: 3
Classifier: License :: OSI Approved :: MIT License
Classifier: Operating System :: Microsoft :: Windows
Requires-Python: >=3.10
License-File: LICENSE.txt
